.gitignore
.gitmodules
MANIFEST.in
Makefile
README.rst
README.txt
READ_BEFORE_RELEASE.txt
bootstrap.py
buildout.cfg
conf.py
distribute_setup.py
setup.cfg
setup.py
docs/HISTORY.txt
docs/INSTALL.txt
docs/LICENSE.GPL
docs/LICENSE.txt
docs/index.rst
docs/installing_ejabberd.rst
docs/troubleshooting.rst
src/collective/__init__.py
src/collective.xmpp.chat.egg-info/PKG-INFO
src/collective.xmpp.chat.egg-info/SOURCES.txt
src/collective.xmpp.chat.egg-info/dependency_links.txt
src/collective.xmpp.chat.egg-info/entry_points.txt
src/collective.xmpp.chat.egg-info/namespace_packages.txt
src/collective.xmpp.chat.egg-info/not-zip-safe
src/collective.xmpp.chat.egg-info/paster_plugins.txt
src/collective.xmpp.chat.egg-info/requires.txt
src/collective.xmpp.chat.egg-info/top_level.txt
src/collective/xmpp/__init__.py
src/collective/xmpp/chat/__init__.py
src/collective/xmpp/chat/configure.zcml
src/collective/xmpp/chat/synci18n.sh
src/collective/xmpp/chat/testing.py
src/collective/xmpp/chat/browser/__init__.py
src/collective/xmpp/chat/browser/configure.zcml
src/collective/xmpp/chat/browser/interfaces.py
src/collective/xmpp/chat/browser/user_details.pt
src/collective/xmpp/chat/browser/userinfo.py
src/collective/xmpp/chat/browser/viewlet.py
src/collective/xmpp/chat/browser/resources/.git
src/collective/xmpp/chat/browser/resources/.gitmodules
src/collective/xmpp/chat/browser/resources/CHANGES.rst
src/collective/xmpp/chat/browser/resources/CONTRIBUTING.rst
src/collective/xmpp/chat/browser/resources/LICENSE_GPL.txt
src/collective/xmpp/chat/browser/resources/LICENSE_MIT.txt
src/collective/xmpp/chat/browser/resources/README.rst
src/collective/xmpp/chat/browser/resources/TODO
src/collective/xmpp/chat/browser/resources/converse.css
src/collective/xmpp/chat/browser/resources/converse.js
src/collective/xmpp/chat/browser/resources/index.html
src/collective/xmpp/chat/browser/resources/main.js
src/collective/xmpp/chat/browser/resources/tests.html
src/collective/xmpp/chat/browser/resources/tests_main.js
src/collective/xmpp/chat/browser/resources/Libraries/app.build.js
src/collective/xmpp/chat/browser/resources/Libraries/backbone.js
src/collective/xmpp/chat/browser/resources/Libraries/jarnxmpp.core.handlers.js
src/collective/xmpp/chat/browser/resources/Libraries/jquery-GPL-LICENSE.txt
src/collective/xmpp/chat/browser/resources/Libraries/jquery-MIT-LICENSE.txt
src/collective/xmpp/chat/browser/resources/Libraries/jquery-ui-1.9.1.custom.js
