Metadata-Version: 1.0
Name: collective.xmpp.chat
Version: 0.2.1
Summary: XMPP-based instant Messaging for Plone
Home-page: http://svn.plone.org/svn/collective/
Author: JC Brand
Author-email: jc@opkode.com
License: GPL
Keywords: xmpp chat messaging
Platform: UNKNOWN
Classifier: Framework :: Plone
Classifier: Programming Language :: Python
